oscli/__init__.py
oscli/auth.py
oscli/config.py
oscli/constants.py
oscli/download.py
oscli/find.py
oscli/main.py
oscli/metadata.py
oscli/utils.py
oscli-0.0.2.dist-info/LICENSE
oscli-0.0.2.dist-info/METADATA
oscli-0.0.2.dist-info/WHEEL
oscli-0.0.2.dist-info/entry_points.txt
oscli-0.0.2.dist-info/top_level.txt
oscli-0.0.2.dist-info/RECORD
