Metadata-Version: 2.1
Name: oscli
Version: 0.0.2
Summary: OpenSubtitles CLI
Home-page: https://github.com/papierukartka/oscli
Author: Krzysztof Ś
Author-email: papierukartka@gmail.com
License: UNKNOWN
Platform: UNKNOWN
Classifier: Programming Language :: Python :: 3
Classifier: License :: OSI Approved :: MIT License
Classifier: Operating System :: OS Independent
Requires-Python: >=3.6
Requires-Dist: Click
Requires-Dist: requests
